{"2622380": "9965417569", "10": "platinummonsterbeatz2", "80": "platinummonsterbeatz2", "100": "platinummonsterbeatz2", "211": "platinummonsterbeatz2", "215": "platinummonsterbeatz2", "218": "platinummonsterbeatz2", "240": "platinummonsterbeatz2", "730": "platinummonsterbeatz2,ridika61", "740": "platinummonsterbeatz2,ridika61", "493490": "platinummonsterbeatz2", "227300": "platinummonsterbeatz2", "421800": "platinummonsterbeatz2", "1948160": "platinummonsterbeatz2", "322170": "platinummonsterbeatz2", "244210": "platinummonsterbeatz2,malao_on_top", "332800": "platinummonsterbeatz2", "477160": "platinummonsterbeatz2", "239140": "platinummonsterbeatz2,jooker702", "284160": "platinummonsterbeatz2", "1293830": "platinummonsterbeatz2", "238320": "platinummonsterbeatz2", "414700": "platinummonsterbeatz2", "1609080": "platinummonsterbeatz2", "629520": "platinummonsterbeatz2", "2381590": "platinummonsterbeatz2", "2878420": "platinummonsterbeatz2", "3097560": "platinummonsterbeatz2", "1995930": "ridika61", "1876070": "ridika61", "2531310": "k8ef0k53f", "1490890": "gm462580", "307690": "gm462580", "1222140": "gamesherodetroit", "271590": "platinummonsterbeatz2,rusdepj,faryalgillani558", "3240220": "platinummonsterbeatz2,rusdepj,faryalgillani558", "1347030": "rusdepj", "1091500": "rusdepj", "1522530": "rusdepj", "50620": "rusdepj", "462780": "rusdepj", "1928940": "rusdepj", "3446850": "rusdepj", "4000": "bibi2paris", "252490": "bibi2paris", "391750": "bibi2paris", "212580": "exneydabro1972", "582660": "exneydabro1972", "298110": "necros13579", "1245620": "kokoteska09", "1069740": "kokoteska09", "1174180": "red_dead_profix", "292030": "red_dead_profix", "345430": "red_dead_profix", "6830": "red_dead_profix", "346110": "jooker702", "376030": "jooker702", "407530": "jooker702", "440900": "jooker702", "931180": "jooker702", "431960": "jooker702", "529180": "jooker702", "1149460": "jooker702", "254700": "jooker702", "924140": "faryalgillani558", "359550": "malao_on_top", "623990": "malao_on_top", "739630": "malao_on_top", "1222680": "malao_on_top", "518790": "malao_on_top", "6880": "redh00dgaming300gier", "20900": "redh00dgaming300gier", "12100": "redh00dgaming300gier", "12110": "redh00dgaming300gier", "12120": "redh00dgaming300gier", "12230": "redh00dgaming300gier", "12240": "redh00dgaming300gier", "12250": "redh00dgaming300gier", "8190": "redh00dgaming300gier", "3700": "redh00dgaming300gier", "220240": "redh00dgaming300gier", "1054650": "rusdepj", "10": "platinummonsterbeatz2", "80": "platinummonsterbeatz2", "100": "platinummonsterbeatz2", "211": "platinummonsterbeatz2,axelturba3660", "215": "platinummonsterbeatz2,axelturba3660", "218": "platinummonsterbeatz2,axelturba3660", "240": "platinummonsterbeatz2,axelturba3660", "730": "platinummonsterbeatz2,ridika61", "740": "platinummonsterbeatz2,ridika61", "493490": "platinummonsterbeatz2", "227300": "platinummonsterbeatz2", "421800": "platinummonsterbeatz2", "1948160": "platinummonsterbeatz2", "322170": "platinummonsterbeatz2,crazycatwastaken", "244210": "platinummonsterbeatz2,malao_on_top", "332800": "platinummonsterbeatz2", "477160": "platinummonsterbeatz2", "239140": "platinummonsterbeatz2,jooker702", "284160": "platinummonsterbeatz2", "1293830": "platinummonsterbeatz2,djaja131415", "238320": "platinummonsterbeatz2", "414700": "platinummonsterbeatz2", "1609080": "platinummonsterbeatz2", "629520": "platinummonsterbeatz2", "2381590": "platinummonsterbeatz2", "2878420": "platinummonsterbeatz2", "3097560": "platinummonsterbeatz2", "271590": "platinummonsterbeatz2,rusdepj,faryalgillani558", "3240220": "platinummonsterbeatz2,rusdepj,faryalgillani558", "1995930": "ridika61", "1876070": "ridika61", "2531310": "k8ef0k53f", "1490890": "gm462580", "307690": "gm462580", "1347030": "rusdepj", "1091500": "rusdepj,Od8Xb8Xf4Iu5", "1522530": "rusdepj", "50620": "rusdepj", "462780": "rusdepj", "1928940": "rusdepj", "3446850": "rusdepj", "1054650": "rusdepj", "212580": "exneydabro1972", "582660": "exneydabro1972", "1174180": "red_dead_profix", "292030": "red_dead_profix,djaja131415", "345430": "red_dead_profix", "6830": "red_dead_profix", "346110": "jooker702", "376030": "jooker702", "407530": "jooker702", "440900": "jooker702", "931180": "jooker702", "431960": "jooker702", "529180": "jooker702", "1149460": "jooker702", "254700": "jooker702", "924140": "faryalgillani558", "359550": "malao_on_top,djaja131415", "623990": "malao_on_top,djaja131415", "739630": "malao_on_top,SKKG65975", "1222680": "malao_on_top,kungterdicon1975", "518790": "malao_on_top", "1627720": "lpuqn62765", "3059070": "djaja131415", "20900": "djaja131415", "48000": "djaja131415", "20920": "djaja131415", "20930": "djaja131415", "360430": "djaja131415", "304430": "djaja131415", "1030840": "djaja131415", "1421480": "djaja131415", "1030830": "djaja131415", "357070": "djaja131415,Od8Xb8Xf4Iu5", "546090": "djaja131415", "701470": "djaja131415", "1836120": "djaja131415", "618140": "djaja131415", "485610": "djaja131415", "1578220": "djaja131415", "400740": "djaja131415", "879510": "djaja131415", "2306590": "djaja131415", "1168660": "djaja131415", "1861970": "djaja131415", "1271710": "djaja131415", "328100": "djaja131415", "222880": "djaja131415", "312530": "djaja131415", "422100": "djaja131415", "47870": "djaja131415", "337360": "djaja131415", "383150": "djaja131415", "383180": "djaja131415", "252950": "djaja131415", "1142710": "djaja131415", "1880380": "djaja131415", "349040": "djaja131415", "1088850": "djaja131415", "472420": "djaja131415", "356190": "djaja131415", "552970": "djaja131415", "1404210": "djaja131415", "508840": "djaja131415", "1929610": "djaja131415", "381210": "djaja131415", "601220": "djaja131415", "218620": "djaja131415", "546560": "realkiwi3484", "1593500": "godofwarsteam123", "2701610": "godofwarsteam123", "2815840": "godofwarsteam123", "2819780": "godofwarsteam123", "2717240": "godofwarsteam123", "2693450": "godofwarsteam123", "1029690": "on3lie4", "3225830": "on3lie4", "814380": "babykeems", "655500": "kungterdicon1975", "1551360": "exqgy03440", "2050650": "exqgy03440", "289070": "exqgy03440", "404350": "exqgy03440", "597260": "exqgy03440", "10150": "axelturba3660", "42680": "axelturba3660", "42690": "axelturba3660", "570": "axelturba3660", "304930": "axelturba3660", "1110390": "axelturba3660", "2138330": "Od8Xb8Xf4Iu5", "583760": "Od8Xb8Xf4Iu5", "1916310": "Od8Xb8Xf4Iu5", "235210": "Od8Xb8Xf4Iu5", "1099640": "Od8Xb8Xf4Iu5", "2303350": "Od8Xb8Xf4Iu5", "1874000": "Od8Xb8Xf4Iu5"}